disquest/__init__.py
disquest/disquestmain.py
disquest-0.2.dist-info/METADATA
disquest-0.2.dist-info/WHEEL
disquest-0.2.dist-info/top_level.txt
disquest-0.2.dist-info/RECORD
